lcdp_kafka_utils/__init__.py
lcdp_kafka_utils/batch_deserializing_consumer.py
lcdp_kafka_utils/cdc_dto_transformer.py
lcdp_kafka_utils/config.py
lcdp_kafka_utils/dto_action_execute.py
lcdp_kafka_utils-1.5.9.dist-info/METADATA
lcdp_kafka_utils-1.5.9.dist-info/WHEEL
lcdp_kafka_utils-1.5.9.dist-info/RECORD
