Metadata-Version: 2.4
Name: lcdp-kafka-utils
Version: 1.5.9
Summary: Kafka Utils
Author: Le Comptoir Des Pharmacies
Author-email: webmaster@lecomptoirdespharmacies.fr
Requires-Python: >=3.8
Classifier: Programming Language :: Python :: 3
Classifier: Programming Language :: Python :: 3.8
Classifier: Programming Language :: Python :: 3.9
Classifier: Programming Language :: Python :: 3.10
Classifier: Programming Language :: Python :: 3.11
Classifier: Programming Language :: Python :: 3.12
Classifier: Programming Language :: Python :: 3.13
Classifier: Programming Language :: Python :: 3.14
Requires-Dist: confluent_kafka (==2.5.0)
Requires-Dist: fastavro (==1.9.4)
